gsync/__init__.py
gsync/gsync.py
git_sync_tool-0.1.8.dist-info/METADATA
git_sync_tool-0.1.8.dist-info/WHEEL
git_sync_tool-0.1.8.dist-info/entry_points.txt
git_sync_tool-0.1.8.dist-info/top_level.txt
git_sync_tool-0.1.8.dist-info/RECORD
