Metadata-Version: 2.1
Name: git_sync_tool
Version: 0.1.8
Summary: Easily sync repos across devices
Home-page: https://github.com/mfacton/git-sync-tool
Author: Miguel Flores-Acton
Author-email: mfacton1@gmail.com
License: The Unlicense
Classifier: Intended Audience :: Developers
Classifier: Topic :: Utilities
Requires-Python: >=3.6
Requires-Dist: colorama
Requires-Dist: prettytable
Requires-Dist: tqdm
Requires-Dist: gitpython
